dbc/__init__.py
dbc/connect.py
dbc/common/__init__.py
dbc/common/constants/__init__.py
dbc/common/constants/connect.py
dbc/common/constants/field.py
dbc/common/constants/misc.py
dbc/common/constants/query.py
dbc/common/constants/query_headers.py
dbc/common/exception/__init__.py
dbc/common/exception/query.py
dbc/domain/__init__.py
dbc/domain/index.py
dbc/domain/reference.py
dbc/domain/table.py
dbc/domain/fields/__init__.py
dbc/domain/fields/blob.py
dbc/domain/fields/bool.py
dbc/domain/fields/clob.py
dbc/domain/fields/date.py
dbc/domain/fields/enum.py
dbc/domain/fields/field.py
dbc/domain/fields/float.py
dbc/domain/fields/int.py
dbc/domain/fields/text.py
dbc/domain/fields/varchar.py
dbc/query/__init__.py
dbc/query/query.py
dbc/service/__init__.py
dbc/service/database_creation.py
dbc/service/lite/__init__.py
dbc/service/lite/field.py
dbc/service/lite/index.py
dbc/service/lite/table.py
simple_dbc-0.0.60.dist-info/LICENSE
simple_dbc-0.0.60.dist-info/METADATA
simple_dbc-0.0.60.dist-info/WHEEL
simple_dbc-0.0.60.dist-info/top_level.txt
simple_dbc-0.0.60.dist-info/RECORD
