Metadata-Version: 2.1
Name: simple-dbc
Version: 0.0.60
Summary: Simple database client for defining database tables and building queries in object-oriented fashion
Home-page: https://github.com/AnthonyRaimondo/simple-dbc
Author: Anthony Raimondo
Author-email: anthonyraimondo7@gmail.com
License: GNU
Platform: UNKNOWN
License-File: LICENSE
Requires-Dist: pydantic
Requires-Dist: mysql-connector-python
Requires-Dist: pandaSuit
